LICENSE
MANIFEST.in
README.rst
setup.py
superblock.py
superblock.egg-info/PKG-INFO
superblock.egg-info/SOURCES.txt
superblock.egg-info/dependency_links.txt
superblock.egg-info/entry_points.txt
superblock.egg-info/top_level.txt