Metadata-Version: 1.1
Name: superblock
Version: 0.2.1
Summary: A script written in Python 2 to analyze the superblock of an ext2/ext3 formatted file.
Home-page: https://github.com/dbrgn/superblock
Author: Danilo Bargen
Author-email: gezuru@gmail.com
License: MIT
Keywords: filesystem superblock ext2 ext3 extfs analyze
Platform: UNKNOWN
Classifier: Development Status :: 4 - Beta
Classifier: Environment :: Console
Classifier: License :: OSI Approved :: MIT License
Classifier: Natural Language :: English
Classifier: Operating System :: MacOS
Classifier: Operating System :: POSIX
Classifier: Programming Language :: Python :: 2
Classifier: Topic :: Education
Classifier: Topic :: System :: Filesystems
Classifier: Topic :: Utilities
